{
  "experiment_name": "cifar10_all_entropy_reg",
  "best_accuracy": 85.59,
  "best_epoch": 98,
  "total_epochs": 100,
  "total_time": 12230.54686665535,
  "final_metrics": {
    "accuracy": 85.32,
    "per_class": {
      "class_0": {
        "precision": 87.72819472616634,
        "recall": 86.5,
        "f1": 87.10976837865056,
        "support": 1000
      },
      "class_1": {
        "precision": 92.31536926147704,
        "recall": 92.5,
        "f1": 92.40759240759242,
        "support": 1000
      },
      "class_2": {
        "precision": 80.99089989888778,
        "recall": 80.10000000000001,
        "f1": 80.54298642533938,
        "support": 1000
      },
      "class_3": {
        "precision": 74.28571428571429,
        "recall": 70.19999999999999,
        "f1": 72.18508997429305,
        "support": 1000
      },
      "class_4": {
        "precision": 81.78368121442125,
        "recall": 86.2,
        "f1": 83.93378773125607,
        "support": 1000
      },
      "class_5": {
        "precision": 78.76984126984127,
        "recall": 79.4,
        "f1": 79.08366533864542,
        "support": 1000
      },
      "class_6": {
        "precision": 86.33301251203079,
        "recall": 89.7,
        "f1": 87.98430603236879,
        "support": 1000
      },
      "class_7": {
        "precision": 88.85480572597137,
        "recall": 86.9,
        "f1": 87.8665318503539,
        "support": 1000
      },
      "class_8": {
        "precision": 91.86746987951807,
        "recall": 91.5,
        "f1": 91.68336673346694,
        "support": 1000
      },
      "class_9": {
        "precision": 89.93020937188435,
        "recall": 90.2,
        "f1": 90.06490264603096,
        "support": 1000
      }
    },
    "macro_precision": 85.28591981459127,
    "macro_recall": 85.32,
    "macro_f1": 85.28619975179976,
    "micro_precision": 85.32,
    "micro_recall": 85.32,
    "micro_f1": 85.32,
    "weighted_precision": 85.28591981459125,
    "weighted_recall": 85.32,
    "weighted_f1": 85.28619975179974,
    "confusion_matrix": [
      [
        865,
        11,
        32,
        11,
        14,
        2,
        6,
        5,
        38,
        16
      ],
      [
        8,
        925,
        1,
        1,
        0,
        1,
        3,
        3,
        9,
        49
      ],
      [
        24,
        0,
        801,
        35,
        42,
        29,
        38,
        20,
        6,
        5
      ],
      [
        9,
        3,
        45,
        702,
        45,
        120,
        43,
        18,
        6,
        9
      ],
      [
        9,
        1,
        36,
        27,
        862,
        14,
        24,
        26,
        1,
        0
      ],
      [
        7,
        1,
        19,
        110,
        27,
        794,
        16,
        24,
        1,
        1
      ],
      [
        2,
        4,
        28,
        26,
        22,
        11,
        897,
        4,
        5,
        1
      ],
      [
        8,
        0,
        16,
        24,
        37,
        35,
        5,
        869,
        2,
        4
      ],
      [
        34,
        14,
        6,
        4,
        3,
        0,
        3,
        5,
        915,
        16
      ],
      [
        20,
        43,
        5,
        5,
        2,
        2,
        4,
        4,
        13,
        902
      ]
    ],
    "top5_accuracy": 99.37,
    "top3_accuracy": 97.43,
    "loss": 0.4952381996402315
  },
  "inference_time": {
    "mean_ms": 14.04419300321024,
    "std_ms": 2.101364912721539,
    "min_ms": 12.565199984237552,
    "max_ms": 21.378799981903285,
    "median_ms": 13.334050017874688
  },
  "gate_entropy": {
    "0": {
      "entropy": 1.4335050203066895,
      "max_entropy": 1.791759469228055,
      "normalized_entropy": 0.8000543850477249,
      "branch_weights": {
        "gabor": 0.8092044591903687,
        "legendre": 0.11562101542949677,
        "chebyshev": 0.033225856721401215,
        "hermite": 0.3592863380908966,
        "fourier": 0.1548597812652588,
        "relu": 0.2412368357181549
      }
    },
    "1": {
      "entropy": 1.4353857256374414,
      "max_entropy": 1.791759469228055,
      "normalized_entropy": 0.8011040266782291,
      "branch_weights": {
        "gabor": 0.5236980319023132,
        "legendre": 0.07014556974172592,
        "chebyshev": 0.053832970559597015,
        "hermite": 0.15044759213924408,
        "fourier": 0.07482579350471497,
        "relu": 0.4264977276325226
      }
    },
    "2": {
      "entropy": 1.7807078558316902,
      "max_entropy": 1.791759469228055,
      "normalized_entropy": 0.9938319771229527,
      "branch_weights": {
        "gabor": 0.8113673329353333,
        "legendre": 0.5968802571296692,
        "chebyshev": 0.6610428690910339,
        "hermite": 0.9113422632217407,
        "fourier": 0.8896944522857666,
        "relu": 0.7761578559875488
      }
    },
    "average_normalized_entropy": 0.864996796282969
  },
  "metrics_history": [
    {
      "epoch": 1,
      "train_loss": 1.8558768863263337,
      "train_accuracy": 32.122,
      "val_loss": 1.6174007547888787,
      "val_accuracy": 39.36,
      "val_precision": 0,
      "val_recall": 0,
      "val_f1": 0,
      "learning_rate": 4.2629714200602604e-05,
      "gate_entropy": 0.9991562076115926,
      "elapsed_time": 122.93123173713684
    },
    {
      "epoch": 2,
      "train_loss": 1.537085663936937,
      "train_accuracy": 43.018,
      "val_loss": 1.4092255527046835,
      "val_accuracy": 48.11,
      "val_precision": 0,
      "val_recall": 0,
      "val_f1": 0,
      "learning_rate": 5.049004264917373e-05,
      "gate_entropy": 0.9992107697563162,
      "elapsed_time": 248.46629524230957
    },
    {
      "epoch": 3,
      "train_loss": 1.4025391713737527,
      "train_accuracy": 48.462,
      "val_loss": 1.3615982889369795,
      "val_accuracy": 50.68,
      "val_precision": 0,
      "val_recall": 0,
      "val_f1": 0,
      "learning_rate": 6.34948586067857e-05,
      "gate_entropy": 0.9992532252952175,
      "elapsed_time": 374.10789346694946
    },
    {
      "epoch": 4,
      "train_loss": 1.314845461827105,
      "train_accuracy": 51.96,
      "val_loss": 1.263765549963447,
      "val_accuracy": 54.67,
      "val_precision": 0,
      "val_recall": 0,
      "val_f1": 0,
      "learning_rate": 8.150166645177212e-05,
      "gate_entropy": 0.9992916015033253,
      "elapsed_time": 500.4016125202179
    },
    {
      "epoch": 5,
      "train_loss": 1.2477523913163968,
      "train_accuracy": 54.616,
      "val_loss": 1.1926278771868177,
      "val_accuracy": 56.98,
      "val_precision": 0,
      "val_recall": 0,
      "val_f1": 0,
      "learning_rate": 0.00010431316302456008,
      "gate_entropy": 0.9993235251210842,
      "elapsed_time": 625.7580006122589
    },
    {
      "epoch": 6,
      "train_loss": 1.1926052074907991,
      "train_accuracy": 57.034,
      "val_loss": 1.1812638093711465,
      "val_accuracy": 57.47,
      "val_precision": 0,
      "val_recall": 0,
      "val_f1": 0,
      "learning_rate": 0.0001316793995065061,
      "gate_entropy": 0.9993291932354978,
      "elapsed_time": 751.1146738529205
    },
    {
      "epoch": 7,
      "train_loss": 1.146680790749962,
      "train_accuracy": 58.824,
      "val_loss": 1.1449520451248072,
      "val_accuracy": 58.3,
      "val_precision": 0,
      "val_recall": 0,
      "val_f1": 0,
      "learning_rate": 0.00016330052014471984,
      "gate_entropy": 0.9993245069080251,
      "elapsed_time": 876.8862633705139
    },
    {
      "epoch": 8,
      "train_loss": 1.1091778969673245,
      "train_accuracy": 60.074,
      "val_loss": 1.0824221520666863,
      "val_accuracy": 62.14,
      "val_precision": 0,
      "val_recall": 0,
      "val_f1": 0,
      "learning_rate": 0.00019883004781427955,
      "gate_entropy": 0.9992523288473553,
      "elapsed_time": 1001.424412727356
    },
    {
      "epoch": 9,
      "train_loss": 1.075540862424904,
      "train_accuracy": 61.504,
      "val_loss": 1.0363308643079867,
      "val_accuracy": 63.12,
      "val_precision": 0,
      "val_recall": 0,
      "val_f1": 0,
      "learning_rate": 0.00023787868041746279,
      "gate_entropy": 0.9991482656285693,
      "elapsed_time": 1126.3750295639038
    },
    {
      "epoch": 10,
      "train_loss": 1.0384336519424262,
      "train_accuracy": 62.748,
      "val_loss": 1.0753381058668634,
      "val_accuracy": 61.53,
      "val_precision": 0,
      "val_recall": 0,
      "val_f1": 0,
      "learning_rate": 0.00028001855652230853,
      "gate_entropy": 0.9989004232374978,
      "elapsed_time": 1251.4487233161926
    },
    {
      "epoch": 11,
      "train_loss": 1.019231149683828,
      "train_accuracy": 64.048,
      "val_loss": 1.2166565781945635,
      "val_accuracy": 57.75,
      "val_precision": 0,
      "val_recall": 0,
      "val_f1": 0,
      "learning_rate": 0.0003247879435012975,
      "gate_entropy": 0.9983701485498394,
      "elapsed_time": 1376.4187750816345
    },
    {
      "epoch": 12,
      "train_loss": 0.9905427284252918,
      "train_accuracy": 64.744,
      "val_loss": 1.2267434866565048,
      "val_accuracy": 57.17,
      "val_precision": 0,
      "val_recall": 0,
      "val_f1": 0,
      "learning_rate": 0.00037169629680155103,
      "gate_entropy": 0.9976988687776687,
      "elapsed_time": 1500.4069204330444
    },
    {
      "epoch": 13,
      "train_loss": 0.9518370318900594,
      "train_accuracy": 66.414,
      "val_loss": 1.0792410426838384,
      "val_accuracy": 62.34,
      "val_precision": 0,
      "val_recall": 0,
      "val_f1": 0,
      "learning_rate": 0.0004202296349114,
      "gate_entropy": 0.9967274770885539,
      "elapsed_time": 1624.7246313095093
    },
    {
      "epoch": 14,
      "train_loss": 0.9271866740168208,
      "train_accuracy": 67.366,
      "val_loss": 1.074950732243289,
      "val_accuracy": 62.31,
      "val_precision": 0,
      "val_recall": 0,
      "val_f1": 0,
      "learning_rate": 0.0004698561711290524,
      "gate_entropy": 0.9952485429020065,
      "elapsed_time": 1750.039068222046
    },
    {
      "epoch": 15,
      "train_loss": 0.9016334586741065,
      "train_accuracy": 68.096,
      "val_loss": 1.0183750018951998,
      "val_accuracy": 64.17,
      "val_precision": 0,
      "val_recall": 0,
      "val_f1": 0,
      "learning_rate": 0.0005200321404252652,
      "gate_entropy": 0.9927596679311635,
      "elapsed_time": 1875.7031290531158
    },
    {
      "epoch": 16,
      "train_loss": 0.8774591435861709,
      "train_accuracy": 69.236,
      "val_loss": 0.8714882708658838,
      "val_accuracy": 69.42,
      "val_precision": 0,
      "val_recall": 0,
      "val_f1": 0,
      "learning_rate": 0.0005702077575542583,
      "gate_entropy": 0.9899664632054028,
      "elapsed_time": 2001.2463765144348
    },
    {
      "epoch": 17,
      "train_loss": 0.8665011531632879,
      "train_accuracy": 69.614,
      "val_loss": 0.9845074016577119,
      "val_accuracy": 65.61,
      "val_precision": 0,
      "val_recall": 0,
      "val_f1": 0,
      "learning_rate": 0.000619833241128998,
      "gate_entropy": 0.9860549426699725,
      "elapsed_time": 2127.0273830890656
    },
    {
      "epoch": 18,
      "train_loss": 0.8464527099638643,
      "train_accuracy": 70.376,
      "val_loss": 0.973861591451487,
      "val_accuracy": 64.92,
      "val_precision": 0,
      "val_recall": 0,
      "val_f1": 0,
      "learning_rate": 0.0006683648376541998,
      "gate_entropy": 0.9806711280948255,
      "elapsed_time": 2251.773109436035
    },
    {
      "epoch": 19,
      "train_loss": 0.8184441890939117,
      "train_accuracy": 71.43,
      "val_loss": 0.8881505215243929,
      "val_accuracy": 69.11,
      "val_precision": 0,
      "val_recall": 0,
      "val_f1": 0,
      "learning_rate": 0.0007152707795108623,
      "gate_entropy": 0.9752629053063867,
      "elapsed_time": 2372.2178540229797
    },
    {
      "epoch": 20,
      "train_loss": 0.7963865581909408,
      "train_accuracy": 72.284,
      "val_loss": 0.809758611735265,
      "val_accuracy": 71.34,
      "val_precision": 0,
      "val_recall": 0,
      "val_f1": 0,
      "learning_rate": 0.0007600371116098481,
      "gate_entropy": 0.9689206207305329,
      "elapsed_time": 2491.827290534973
    },
    {
      "epoch": 21,
      "train_loss": 0.7844177019946715,
      "train_accuracy": 72.59,
      "val_loss": 0.8715604184919102,
      "val_accuracy": 69.39,
      "val_precision": 0,
      "val_recall": 0,
      "val_f1": 0,
      "learning_rate": 0.0008021733228710335,
      "gate_entropy": 0.9626630317813937,
      "elapsed_time": 2611.543848991394
    },
    {
      "epoch": 22,
      "train_loss": 0.761262542641986,
      "train_accuracy": 73.732,
      "val_loss": 0.8453950883856245,
      "val_accuracy": 70.63,
      "val_precision": 0,
      "val_recall": 0,
      "val_f1": 0,
      "learning_rate": 0.000841217720823114,
      "gate_entropy": 0.9554321291563991,
      "elapsed_time": 2731.216873407364
    },
    {
      "epoch": 23,
      "train_loss": 0.7442467663141773,
      "train_accuracy": 74.2,
      "val_loss": 1.0658880297545414,
      "val_accuracy": 64.98,
      "val_precision": 0,
      "val_recall": 0,
      "val_f1": 0,
      "learning_rate": 0.0008767424904338039,
      "gate_entropy": 0.9489996986637932,
      "elapsed_time": 2851.7021737098694
    },
    {
      "epoch": 24,
      "train_loss": 0.7295385250426314,
      "train_accuracy": 74.602,
      "val_loss": 0.8377486966597806,
      "val_accuracy": 70.82,
      "val_precision": 0,
      "val_recall": 0,
      "val_f1": 0,
      "learning_rate": 0.0009083583817401097,
      "gate_entropy": 0.9412298899316273,
      "elapsed_time": 2971.8106417655945
    },
    {
      "epoch": 25,
      "train_loss": 0.7141253337302171,
      "train_accuracy": 75.258,
      "val_loss": 0.918804859849298,
      "val_accuracy": 68.29,
      "val_precision": 0,
      "val_recall": 0,
      "val_f1": 0,
      "learning_rate": 0.0009357189749156447,
      "gate_entropy": 0.9339186375198919,
      "elapsed_time": 3092.1332886219025
    },
    {
      "epoch": 26,
      "train_loss": 0.6882222094727904,
      "train_accuracy": 76.068,
      "val_loss": 0.9135186338120964,
      "val_accuracy": 69.97,
      "val_precision": 0,
      "val_recall": 0,
      "val_f1": 0,
      "learning_rate": 0.0009585244760420311,
      "gate_entropy": 0.9268958533937953,
      "elapsed_time": 3209.8144562244415
    },
    {
      "epoch": 27,
      "train_loss": 0.6800582811350713,
      "train_accuracy": 76.468,
      "val_loss": 0.6875445406148388,
      "val_accuracy": 76.35,
      "val_precision": 0,
      "val_recall": 0,
      "val_f1": 0,
      "learning_rate": 0.000976525001993586,
      "gate_entropy": 0.920441410458379,
      "elapsed_time": 3324.986541748047
    },
    {
      "epoch": 28,
      "train_loss": 0.6620573428890589,
      "train_accuracy": 77.364,
      "val_loss": 0.8798608407852756,
      "val_accuracy": 69.47,
      "val_precision": 0,
      "val_recall": 0,
      "val_f1": 0,
      "learning_rate": 0.000989523318442338,
      "gate_entropy": 0.9158898508894788,
      "elapsed_time": 3449.4916949272156
    },
    {
      "epoch": 29,
      "train_loss": 0.6452055778116217,
      "train_accuracy": 77.83,
      "val_loss": 0.6999030506155294,
      "val_accuracy": 76.38,
      "val_precision": 0,
      "val_recall": 0,
      "val_f1": 0,
      "learning_rate": 0.0009973770009826654,
      "gate_entropy": 0.9081444895719301,
      "elapsed_time": 3575.5609793663025
    },
    {
      "epoch": 30,
      "train_loss": 0.6363642684486516,
      "train_accuracy": 78.158,
      "val_loss": 0.6484823414854183,
      "val_accuracy": 77.66,
      "val_precision": 0,
      "val_recall": 0,
      "val_f1": 0,
      "learning_rate": 0.0009999999991765667,
      "gate_entropy": 0.9036015389615389,
      "elapsed_time": 3701.9400374889374
    },
    {
      "epoch": 31,
      "train_loss": 0.6184424920307706,
      "train_accuracy": 78.87,
      "val_loss": 0.6869352532040541,
      "val_accuracy": 76.21,
      "val_precision": 0,
      "val_recall": 0,
      "val_f1": 0,
      "learning_rate": 0.0009994952470445146,
      "gate_entropy": 0.8973623791993964,
      "elapsed_time": 3828.007355928421
    },
    {
      "epoch": 32,
      "train_loss": 0.6022112240343143,
      "train_accuracy": 79.25,
      "val_loss": 0.672500427741154,
      "val_accuracy": 76.86,
      "val_precision": 0,
      "val_recall": 0,
      "val_f1": 0,
      "learning_rate": 0.0009979845819867892,
      "gate_entropy": 0.8933409620869502,
      "elapsed_time": 3953.83718419075
    },
    {
      "epoch": 33,
      "train_loss": 0.5865326224995391,
      "train_accuracy": 79.778,
      "val_loss": 0.6647042178424301,
      "val_accuracy": 77.01,
      "val_precision": 0,
      "val_recall": 0,
      "val_f1": 0,
      "learning_rate": 0.000995471046281774,
      "gate_entropy": 0.889513102838447,
      "elapsed_time": 4081.0565752983093
    },
    {
      "epoch": 34,
      "train_loss": 0.5731595726802831,
      "train_accuracy": 80.024,
      "val_loss": 0.6151181616980559,
      "val_accuracy": 78.73,
      "val_precision": 0,
      "val_recall": 0,
      "val_f1": 0,
      "learning_rate": 0.0009919597018558705,
      "gate_entropy": 0.8861825493358239,
      "elapsed_time": 4207.1856372356415
    },
    {
      "epoch": 35,
      "train_loss": 0.5566644783481918,
      "train_accuracy": 80.688,
      "val_loss": 0.6117695363084222,
      "val_accuracy": 78.94,
      "val_precision": 0,
      "val_recall": 0,
      "val_f1": 0,
      "learning_rate": 0.000987457620089454,
      "gate_entropy": 0.8821649495823133,
      "elapsed_time": 4333.565474748611
    },
    {
      "epoch": 36,
      "train_loss": 0.5458957520706574,
      "train_accuracy": 81.078,
      "val_loss": 0.5967973411842517,
      "val_accuracy": 79.31,
      "val_precision": 0,
      "val_recall": 0,
      "val_f1": 0,
      "learning_rate": 0.0009819738675760526,
      "gate_entropy": 0.8782342616358044,
      "elapsed_time": 4459.58966588974
    },
    {
      "epoch": 37,
      "train_loss": 0.5364356136230557,
      "train_accuracy": 81.334,
      "val_loss": 0.6242989180194345,
      "val_accuracy": 78.72,
      "val_precision": 0,
      "val_recall": 0,
      "val_f1": 0,
      "learning_rate": 0.0009755194878634366,
      "gate_entropy": 0.874130063316099,
      "elapsed_time": 4585.911001443863
    },
    {
      "epoch": 38,
      "train_loss": 0.5265602366927334,
      "train_accuracy": 81.942,
      "val_loss": 0.6039129991060609,
      "val_accuracy": 79.31,
      "val_precision": 0,
      "val_recall": 0,
      "val_f1": 0,
      "learning_rate": 0.0009681074792133812,
      "gate_entropy": 0.8724144218849524,
      "elapsed_time": 4711.728484153748
    },
    {
      "epoch": 39,
      "train_loss": 0.518216775925568,
      "train_accuracy": 82.184,
      "val_loss": 0.6253603008712173,
      "val_accuracy": 78.98,
      "val_precision": 0,
      "val_recall": 0,
      "val_f1": 0,
      "learning_rate": 0.000959752768424898,
      "gate_entropy": 0.8720263524423811,
      "elapsed_time": 4837.689162731171
    },
    {
      "epoch": 40,
      "train_loss": 0.507577531458929,
      "train_accuracy": 82.508,
      "val_loss": 0.570876007247123,
      "val_accuracy": 80.33,
      "val_precision": 0,
      "val_recall": 0,
      "val_f1": 0,
      "learning_rate": 0.0009504721807736481,
      "gate_entropy": 0.871263120001441,
      "elapsed_time": 4972.201320886612
    },
    {
      "epoch": 41,
      "train_loss": 0.4985193538924922,
      "train_accuracy": 82.942,
      "val_loss": 0.5604284515806065,
      "val_accuracy": 80.84,
      "val_precision": 0,
      "val_recall": 0,
      "val_f1": 0,
      "learning_rate": 0.0009402844061280762,
      "gate_entropy": 0.8693042165683216,
      "elapsed_time": 5106.518579006195
    },
    {
      "epoch": 42,
      "train_loss": 0.4916615520063264,
      "train_accuracy": 83.04,
      "val_loss": 0.5594086675507248,
      "val_accuracy": 81.4,
      "val_precision": 0,
      "val_recall": 0,
      "val_f1": 0,
      "learning_rate": 0.0009292099613105025,
      "gate_entropy": 0.8683162323017278,
      "elapsed_time": 5229.560727596283
    },
    {
      "epoch": 43,
      "train_loss": 0.4801399974376344,
      "train_accuracy": 83.408,
      "val_loss": 0.5563175926922234,
      "val_accuracy": 81.08,
      "val_precision": 0,
      "val_recall": 0,
      "val_f1": 0,
      "learning_rate": 0.0009172711487789735,
      "gate_entropy": 0.867578845205891,
      "elapsed_time": 5351.5731592178345
    },
    {
      "epoch": 44,
      "train_loss": 0.47058623087832996,
      "train_accuracy": 83.794,
      "val_loss": 0.5687900327952804,
      "val_accuracy": 81.04,
      "val_precision": 0,
      "val_recall": 0,
      "val_f1": 0,
      "learning_rate": 0.0009044920117130792,
      "gate_entropy": 0.8669111193745925,
      "elapsed_time": 5473.177786111832
    },
    {
      "epoch": 45,
      "train_loss": 0.4606534727965779,
      "train_accuracy": 84.214,
      "val_loss": 0.5209223728650695,
      "val_accuracy": 82.2,
      "val_precision": 0,
      "val_recall": 0,
      "val_f1": 0,
      "learning_rate": 0.000890898285594189,
      "gate_entropy": 0.8660613278463659,
      "elapsed_time": 5595.147212743759
    },
    {
      "epoch": 46,
      "train_loss": 0.456694860039922,
      "train_accuracy": 84.15,
      "val_loss": 0.5554852130686402,
      "val_accuracy": 81.34,
      "val_precision": 0,
      "val_recall": 0,
      "val_f1": 0,
      "learning_rate": 0.0008765173463776176,
      "gate_entropy": 0.8661011111948499,
      "elapsed_time": 5717.271864891052
    },
    {
      "epoch": 47,
      "train_loss": 0.44365975390309875,
      "train_accuracy": 84.614,
      "val_loss": 0.5670371790220783,
      "val_accuracy": 80.4,
      "val_precision": 0,
      "val_recall": 0,
      "val_f1": 0,
      "learning_rate": 0.000861378155361094,
      "gate_entropy": 0.8664337529234672,
      "elapsed_time": 5839.692269086838
    },
    {
      "epoch": 48,
      "train_loss": 0.4377045761555662,
      "train_accuracy": 84.934,
      "val_loss": 0.5725849499558188,
      "val_accuracy": 80.61,
      "val_precision": 0,
      "val_recall": 0,
      "val_f1": 0,
      "learning_rate": 0.0008455112008605618,
      "gate_entropy": 0.8661978559040285,
      "elapsed_time": 5962.078840017319
    },
    {
      "epoch": 49,
      "train_loss": 0.4283515764281268,
      "train_accuracy": 85.102,
      "val_loss": 0.5241179079007191,
      "val_accuracy": 82.23,
      "val_precision": 0,
      "val_recall": 0,
      "val_f1": 0,
      "learning_rate": 0.0008289484368107694,
      "gate_entropy": 0.8658920734403225,
      "elapsed_time": 6091.847888469696
    },
    {
      "epoch": 50,
      "train_loss": 0.42581776489534645,
      "train_accuracy": 85.176,
      "val_loss": 0.5099117279432381,
      "val_accuracy": 82.59,
      "val_precision": 0,
      "val_recall": 0,
      "val_f1": 0,
      "learning_rate": 0.0008117232184142969,
      "gate_entropy": 0.8659698408894522,
      "elapsed_time": 6224.640421390533
    },
    {
      "epoch": 51,
      "train_loss": 0.4132891507328624,
      "train_accuracy": 85.742,
      "val_loss": 0.5279319355632089,
      "val_accuracy": 81.86,
      "val_precision": 0,
      "val_recall": 0,
      "val_f1": 0,
      "learning_rate": 0.0007938702349686175,
      "gate_entropy": 0.8664314507391225,
      "elapsed_time": 6357.046172857285
    },
    {
      "epoch": 52,
      "train_loss": 0.40846894885344276,
      "train_accuracy": 85.842,
      "val_loss": 0.5070380431831263,
      "val_accuracy": 82.6,
      "val_precision": 0,
      "val_recall": 0,
      "val_f1": 0,
      "learning_rate": 0.0007754254400064685,
      "gate_entropy": 0.8660045532543198,
      "elapsed_time": 6487.468712091446
    },
    {
      "epoch": 53,
      "train_loss": 0.3997439380230196,
      "train_accuracy": 86.126,
      "val_loss": 0.5356395094637658,
      "val_accuracy": 82.11,
      "val_precision": 0,
      "val_recall": 0,
      "val_f1": 0,
      "learning_rate": 0.000756425978890222,
      "gate_entropy": 0.8656247812632873,
      "elapsed_time": 6609.2356860637665
    },
    {
      "epoch": 54,
      "train_loss": 0.39660466748201634,
      "train_accuracy": 86.038,
      "val_loss": 0.502214899108668,
      "val_accuracy": 82.92,
      "val_precision": 0,
      "val_recall": 0,
      "val_f1": 0,
      "learning_rate": 0.0007369101140060682,
      "gate_entropy": 0.866709708533751,
      "elapsed_time": 6730.712185382843
    },
    {
      "epoch": 55,
      "train_loss": 0.3880446179557944,
      "train_accuracy": 86.38,
      "val_loss": 0.5485645157706206,
      "val_accuracy": 81.75,
      "val_precision": 0,
      "val_recall": 0,
      "val_f1": 0,
      "learning_rate": 0.0007169171477086606,
      "gate_entropy": 0.8666226768425297,
      "elapsed_time": 6852.894166707993
    },
    {
      "epoch": 56,
      "train_loss": 0.3806629612508332,
      "train_accuracy": 86.712,
      "val_loss": 0.5312014309463987,
      "val_accuracy": 82.3,
      "val_precision": 0,
      "val_recall": 0,
      "val_f1": 0,
      "learning_rate": 0.000696487343171406,
      "gate_entropy": 0.866167845478269,
      "elapsed_time": 6974.586194753647
    },
    {
      "epoch": 57,
      "train_loss": 0.3742405926746786,
      "train_accuracy": 86.912,
      "val_loss": 0.5224343287717005,
      "val_accuracy": 82.43,
      "val_precision": 0,
      "val_recall": 0,
      "val_f1": 0,
      "learning_rate": 0.0006756618433017903,
      "gate_entropy": 0.866361655390432,
      "elapsed_time": 7096.754041671753
    },
    {
      "epoch": 58,
      "train_loss": 0.3690788454049841,
      "train_accuracy": 87.03,
      "val_loss": 0.5182178261553406,
      "val_accuracy": 82.53,
      "val_precision": 0,
      "val_recall": 0,
      "val_f1": 0,
      "learning_rate": 0.0006544825878850387,
      "gate_entropy": 0.865987718909284,
      "elapsed_time": 7218.373824596405
    },
    {
      "epoch": 59,
      "train_loss": 0.3597107434268955,
      "train_accuracy": 87.418,
      "val_loss": 0.4921784428464379,
      "val_accuracy": 83.31,
      "val_precision": 0,
      "val_recall": 0,
      "val_f1": 0,
      "learning_rate": 0.0006329922291229694,
      "gate_entropy": 0.8656465624578452,
      "elapsed_time": 7339.919180631638
    },
    {
      "epoch": 60,
      "train_loss": 0.34938229353683986,
      "train_accuracy": 87.706,
      "val_loss": 0.5000979625115729,
      "val_accuracy": 83.68,
      "val_precision": 0,
      "val_recall": 0,
      "val_f1": 0,
      "learning_rate": 0.0006112340457381357,
      "gate_entropy": 0.8652503513384118,
      "elapsed_time": 7461.571295261383
    },
    {
      "epoch": 61,
      "train_loss": 0.34827421561760064,
      "train_accuracy": 87.806,
      "val_loss": 0.49454544949683416,
      "val_accuracy": 83.4,
      "val_precision": 0,
      "val_recall": 0,
      "val_f1": 0,
      "learning_rate": 0.0005892518558162386,
      "gate_entropy": 0.865898989798514,
      "elapsed_time": 7584.093354701996
    },
    {
      "epoch": 62,
      "train_loss": 0.3405081656620935,
      "train_accuracy": 88.16,
      "val_loss": 0.5100459154624088,
      "val_accuracy": 83.1,
      "val_precision": 0,
      "val_recall": 0,
      "val_f1": 0,
      "learning_rate": 0.000567089928562333,
      "gate_entropy": 0.8652893572517648,
      "elapsed_time": 7720.099822759628
    },
    {
      "epoch": 63,
      "train_loss": 0.3360797268674349,
      "train_accuracy": 88.256,
      "val_loss": 0.49469845984012456,
      "val_accuracy": 83.53,
      "val_precision": 0,
      "val_recall": 0,
      "val_f1": 0,
      "learning_rate": 0.0005447928951485408,
      "gate_entropy": 0.8659482240045101,
      "elapsed_time": 7856.292425394058
    },
    {
      "epoch": 64,
      "train_loss": 0.32455880926621844,
      "train_accuracy": 88.564,
      "val_loss": 0.48275516851312794,
      "val_accuracy": 84.34,
      "val_precision": 0,
      "val_recall": 0,
      "val_f1": 0,
      "learning_rate": 0.0005224056588328095,
      "gate_entropy": 0.8652638285838067,
      "elapsed_time": 7984.256950855255
    },
    {
      "epoch": 65,
      "train_loss": 0.3182394467008388,
      "train_accuracy": 88.71,
      "val_loss": 0.4902281540024812,
      "val_accuracy": 83.77,
      "val_precision": 0,
      "val_recall": 0,
      "val_f1": 0,
      "learning_rate": 0.0004999733045297269,
      "gate_entropy": 0.8665326271331312,
      "elapsed_time": 8112.6378655433655
    },
    {
      "epoch": 66,
      "train_loss": 0.31231363428294506,
      "train_accuracy": 88.906,
      "val_loss": 0.4956017624420725,
      "val_accuracy": 83.92,
      "val_precision": 0,
      "val_recall": 0,
      "val_f1": 0,
      "learning_rate": 0.00047754100801550243,
      "gate_entropy": 0.8663949086957162,
      "elapsed_time": 8240.727967739105
    },
    {
      "epoch": 67,
      "train_loss": 0.30300383153550153,
      "train_accuracy": 89.246,
      "val_loss": 0.5006316450371104,
      "val_accuracy": 83.73,
      "val_precision": 0,
      "val_recall": 0,
      "val_f1": 0,
      "learning_rate": 0.000455153944949967,
      "gate_entropy": 0.8655439173756942,
      "elapsed_time": 8368.731667757034
    },
    {
      "epoch": 68,
      "train_loss": 0.30082278493839454,
      "train_accuracy": 89.4,
      "val_loss": 0.49163391683132024,
      "val_accuracy": 84.03,
      "val_precision": 0,
      "val_recall": 0,
      "val_f1": 0,
      "learning_rate": 0.00043285719989880506,
      "gate_entropy": 0.8655744185673737,
      "elapsed_time": 8497.02625155449
    },
    {
      "epoch": 69,
      "train_loss": 0.2951013504925286,
      "train_accuracy": 89.67,
      "val_loss": 0.48603653936249436,
      "val_accuracy": 84.2,
      "val_precision": 0,
      "val_recall": 0,
      "val_f1": 0,
      "learning_rate": 0.00041069567553924063,
      "gate_entropy": 0.8658667047933267,
      "elapsed_time": 8624.651104688644
    },
    {
      "epoch": 70,
      "train_loss": 0.28554719411160634,
      "train_accuracy": 89.834,
      "val_loss": 0.48602523536059505,
      "val_accuracy": 84.64,
      "val_precision": 0,
      "val_recall": 0,
      "val_f1": 0,
      "learning_rate": 0.0003887140022320194,
      "gate_entropy": 0.8659346680969513,
      "elapsed_time": 8750.04951119423
    },
    {
      "epoch": 71,
      "train_loss": 0.285606640622096,
      "train_accuracy": 90.002,
      "val_loss": 0.49980009646172735,
      "val_accuracy": 83.95,
      "val_precision": 0,
      "val_recall": 0,
      "val_f1": 0,
      "learning_rate": 0.00036695644814180376,
      "gate_entropy": 0.8657458469187951,
      "elapsed_time": 8870.013126850128
    },
    {
      "epoch": 72,
      "train_loss": 0.27080789568555325,
      "train_accuracy": 90.466,
      "val_loss": 0.5040591341105236,
      "val_accuracy": 84.41,
      "val_precision": 0,
      "val_recall": 0,
      "val_f1": 0,
      "learning_rate": 0.0003454668300869786,
      "gate_entropy": 0.8654815762884885,
      "elapsed_time": 8989.795908212662
    },
    {
      "epoch": 73,
      "train_loss": 0.2699690576919052,
      "train_accuracy": 90.484,
      "val_loss": 0.4812273114540015,
      "val_accuracy": 84.66,
      "val_precision": 0,
      "val_recall": 0,
      "val_f1": 0,
      "learning_rate": 0.00032428842529841156,
      "gate_entropy": 0.8652651742603273,
      "elapsed_time": 9110.550290346146
    },
    {
      "epoch": 74,
      "train_loss": 0.2646085218719357,
      "train_accuracy": 90.846,
      "val_loss": 0.4925493513512763,
      "val_accuracy": 84.29,
      "val_precision": 0,
      "val_recall": 0,
      "val_f1": 0,
      "learning_rate": 0.0003034638842648689,
      "gate_entropy": 0.8650944723452412,
      "elapsed_time": 9230.637610912323
    },
    {
      "epoch": 75,
      "train_loss": 0.26172766159943606,
      "train_accuracy": 90.702,
      "val_loss": 0.4860248444186654,
      "val_accuracy": 84.68,
      "val_precision": 0,
      "val_recall": 0,
      "val_f1": 0,
      "learning_rate": 0.0002830351448406076,
      "gate_entropy": 0.8652994277639006,
      "elapsed_time": 9349.375175952911
    },
    {
      "epoch": 76,
      "train_loss": 0.2568338365744218,
      "train_accuracy": 90.918,
      "val_loss": 0.48781984807199735,
      "val_accuracy": 84.75,
      "val_precision": 0,
      "val_recall": 0,
      "val_f1": 0,
      "learning_rate": 0.00026304334778811804,
      "gate_entropy": 0.8654379756898201,
      "elapsed_time": 9471.12259721756
    },
    {
      "epoch": 77,
      "train_loss": 0.2520736020601467,
      "train_accuracy": 91.058,
      "val_loss": 0.4795921707798721,
      "val_accuracy": 85.0,
      "val_precision": 0,
      "val_recall": 0,
      "val_f1": 0,
      "learning_rate": 0.00024352875392610228,
      "gate_entropy": 0.8653625538251298,
      "elapsed_time": 9592.107550621033
    },
    {
      "epoch": 78,
      "train_loss": 0.24467640187677062,
      "train_accuracy": 91.354,
      "val_loss": 0.48596655126589877,
      "val_accuracy": 84.94,
      "val_precision": 0,
      "val_recall": 0,
      "val_f1": 0,
      "learning_rate": 0.00022453066304954587,
      "gate_entropy": 0.8656407788493636,
      "elapsed_time": 9713.498046636581
    },
    {
      "epoch": 79,
      "train_loss": 0.24377703105987947,
      "train_accuracy": 91.4,
      "val_loss": 0.4816913240274806,
      "val_accuracy": 84.9,
      "val_precision": 0,
      "val_recall": 0,
      "val_f1": 0,
      "learning_rate": 0.00020608733478515748,
      "gate_entropy": 0.8657717027967591,
      "elapsed_time": 9836.110823392868
    },
    {
      "epoch": 80,
      "train_loss": 0.23408368244633804,
      "train_accuracy": 91.824,
      "val_loss": 0.49822317633279567,
      "val_accuracy": 84.73,
      "val_precision": 0,
      "val_recall": 0,
      "val_f1": 0,
      "learning_rate": 0.00018823591154157546,
      "gate_entropy": 0.8652047302164533,
      "elapsed_time": 9955.632430553436
    },
    {
      "epoch": 81,
      "train_loss": 0.2358463098154501,
      "train_accuracy": 91.708,
      "val_loss": 0.4873596020754735,
      "val_accuracy": 84.92,
      "val_precision": 0,
      "val_recall": 0,
      "val_f1": 0,
      "learning_rate": 0.00017101234370949802,
      "gate_entropy": 0.8652831638995062,
      "elapsed_time": 10075.310962677002
    },
    {
      "epoch": 82,
      "train_loss": 0.22767272527279603,
      "train_accuracy": 92.088,
      "val_loss": 0.49624146193645563,
      "val_accuracy": 84.85,
      "val_precision": 0,
      "val_recall": 0,
      "val_f1": 0,
      "learning_rate": 0.00015445131726238114,
      "gate_entropy": 0.865017553122693,
      "elapsed_time": 10197.17470574379
    },
    {
      "epoch": 83,
      "train_loss": 0.22341962795599798,
      "train_accuracy": 92.078,
      "val_loss": 0.5026764179680757,
      "val_accuracy": 84.75,
      "val_precision": 0,
      "val_recall": 0,
      "val_f1": 0,
      "learning_rate": 0.00013858618390350454,
      "gate_entropy": 0.8647210135599078,
      "elapsed_time": 10317.13713145256
    },
    {
      "epoch": 84,
      "train_loss": 0.22159673093968188,
      "train_accuracy": 92.33,
      "val_loss": 0.48811330475435133,
      "val_accuracy": 85.11,
      "val_precision": 0,
      "val_recall": 0,
      "val_f1": 0,
      "learning_rate": 0.00012344889390007895,
      "gate_entropy": 0.865084652564077,
      "elapsed_time": 10437.288416862488
    },
    {
      "epoch": 85,
      "train_loss": 0.21717567638734647,
      "train_accuracy": 92.286,
      "val_loss": 0.48588549084724136,
      "val_accuracy": 85.16,
      "val_precision": 0,
      "val_recall": 0,
      "val_f1": 0,
      "learning_rate": 0.00010906993173966144,
      "gate_entropy": 0.8649699838024169,
      "elapsed_time": 10558.959657430649
    },
    {
      "epoch": 86,
      "train_loss": 0.21714054804076166,
      "train_accuracy": 92.324,
      "val_loss": 0.4917117005131047,
      "val_accuracy": 85.21,
      "val_precision": 0,
      "val_recall": 0,
      "val_f1": 0,
      "learning_rate": 9.547825473845246e-05,
      "gate_entropy": 0.8648815516658086,
      "elapsed_time": 10680.807451248169
    },
    {
      "epoch": 87,
      "train_loss": 0.21115554618599164,
      "train_accuracy": 92.644,
      "val_loss": 0.4906307621176835,
      "val_accuracy": 85.33,
      "val_precision": 0,
      "val_recall": 0,
      "val_f1": 0,
      "learning_rate": 8.270123472511686e-05,
      "gate_entropy": 0.8650889914458665,
      "elapsed_time": 10800.867003679276
    },
    {
      "epoch": 88,
      "train_loss": 0.21193604753888629,
      "train_accuracy": 92.548,
      "val_loss": 0.49302812585025835,
      "val_accuracy": 85.32,
      "val_precision": 0,
      "val_recall": 0,
      "val_f1": 0,
      "learning_rate": 7.076460291756155e-05,
      "gate_entropy": 0.8650895075545666,
      "elapsed_time": 10919.147649765015
    },
    {
      "epoch": 89,
      "train_loss": 0.20763943212397415,
      "train_accuracy": 92.62,
      "val_loss": 0.49786858735190836,
      "val_accuracy": 85.05,
      "val_precision": 0,
      "val_recall": 0,
      "val_f1": 0,
      "learning_rate": 5.969239810368918e-05,
      "gate_entropy": 0.8651430541618633,
      "elapsed_time": 11039.526803255081
    },
    {
      "epoch": 90,
      "train_loss": 0.20636454336535748,
      "train_accuracy": 92.684,
      "val_loss": 0.49512699578598046,
      "val_accuracy": 85.52,
      "val_precision": 0,
      "val_recall": 0,
      "val_f1": 0,
      "learning_rate": 4.950691823047621e-05,
      "gate_entropy": 0.8650375721512301,
      "elapsed_time": 11160.048370361328
    },
    {
      "epoch": 91,
      "train_loss": 0.20445689116425983,
      "train_accuracy": 92.826,
      "val_loss": 0.49402951577286813,
      "val_accuracy": 85.4,
      "val_precision": 0,
      "val_recall": 0,
      "val_f1": 0,
      "learning_rate": 4.022867549887718e-05,
      "gate_entropy": 0.8650631874158526,
      "elapsed_time": 11281.43038892746
    },
    {
      "epoch": 92,
      "train_loss": 0.19977533653892976,
      "train_accuracy": 92.982,
      "val_loss": 0.4990488827987841,
      "val_accuracy": 85.36,
      "val_precision": 0,
      "val_recall": 0,
      "val_f1": 0,
      "learning_rate": 3.187635505498053e-05,
      "gate_entropy": 0.8650715222291595,
      "elapsed_time": 11400.94871377945
    },
    {
      "epoch": 93,
      "train_loss": 0.2028000376775594,
      "train_accuracy": 92.698,
      "val_loss": 0.49902586097929885,
      "val_accuracy": 85.44,
      "val_precision": 0,
      "val_recall": 0,
      "val_f1": 0,
      "learning_rate": 2.446677736061147e-05,
      "gate_entropy": 0.865069753690528,
      "elapsed_time": 11519.90403842926
    },
    {
      "epoch": 94,
      "train_loss": 0.1974697555069957,
      "train_accuracy": 93.012,
      "val_loss": 0.49910965969987736,
      "val_accuracy": 85.21,
      "val_precision": 0,
      "val_recall": 0,
      "val_f1": 0,
      "learning_rate": 1.801486431916034e-05,
      "gate_entropy": 0.8650372765241942,
      "elapsed_time": 11638.679603338242
    },
    {
      "epoch": 95,
      "train_loss": 0.19520873220070548,
      "train_accuracy": 93.136,
      "val_loss": 0.4999153914914769,
      "val_accuracy": 85.28,
      "val_precision": 0,
      "val_recall": 0,
      "val_f1": 0,
      "learning_rate": 1.253360922485522e-05,
      "gate_entropy": 0.8649743284535686,
      "elapsed_time": 11757.860008955002
    },
    {
      "epoch": 96,
      "train_loss": 0.1964275785567015,
      "train_accuracy": 93.04,
      "val_loss": 0.49960778966830793,
      "val_accuracy": 85.4,
      "val_precision": 0,
      "val_recall": 0,
      "val_f1": 0,
      "learning_rate": 8.034050595996071e-06,
      "gate_entropy": 0.8650025730123584,
      "elapsed_time": 11877.035879135132
    },
    {
      "epoch": 97,
      "train_loss": 0.194346772745023,
      "train_accuracy": 93.134,
      "val_loss": 0.5010584014806019,
      "val_accuracy": 85.41,
      "val_precision": 0,
      "val_recall": 0,
      "val_f1": 0,
      "learning_rate": 4.525249944848247e-06,
      "gate_entropy": 0.8650063285769788,
      "elapsed_time": 11963.502717018127
    },
    {
      "epoch": 98,
      "train_loss": 0.19679749401672111,
      "train_accuracy": 92.898,
      "val_loss": 0.494782504287495,
      "val_accuracy": 85.59,
      "val_precision": 0,
      "val_recall": 0,
      "val_f1": 0,
      "learning_rate": 2.0142735289629757e-06,
      "gate_entropy": 0.8649980834023161,
      "elapsed_time": 12044.867723226547
    },
    {
      "epoch": 99,
      "train_loss": 0.19251426938168534,
      "train_accuracy": 93.212,
      "val_loss": 0.4967410846310816,
      "val_accuracy": 85.39,
      "val_precision": 0,
      "val_recall": 0,
      "val_f1": 0,
      "learning_rate": 5.061781206742738e-07,
      "gate_entropy": 0.8649974253373472,
      "elapsed_time": 12126.052473068237
    },
    {
      "epoch": 100,
      "train_loss": 0.19182500707657288,
      "train_accuracy": 93.06,
      "val_loss": 0.4952381996402315,
      "val_accuracy": 85.32,
      "val_precision": 0,
      "val_recall": 0,
      "val_f1": 0,
      "learning_rate": 4.0008234333029405e-09,
      "gate_entropy": 0.864996796282969,
      "elapsed_time": 12207.425986528397
    }
  ],
  "parameter_count": 1355947
}